Workbook

Sheet Assets
A1: Asset Type | B1: Description | C1: Quantity | D1: Price | E1: Market Value
A2: Equity | B2: ASML Holding | C2: 200 | D2: 650 | E2: =+D2*C2 -> 130000
A3: Equity | B3: LVMH | C3: 150 | D3: 720 | E3: =+D3*C3 -> 108000
A4: Equity | B4: Microsoft Corp | C4: 300 | D4: 410 | E4: =+D4*C4 -> 123000
A5: Cash | B5: EUR cash account | E5: 133300
A6: Receivable | B6: ASML dividend receivable | E6: 3200
A7: Accrued Income | B7: Accrued bond interest | E7: 1150
A8: Fund-of-Funds investment | B8: Consolidated position — 3 UCITS sub-funds | E8: =+'Fund-of-Funds'!E5 -> 134500
A9: TOTAL ASSETS | E9: =+SUM(E2:E8) -> 633150

Sheet Liabilities
A1: Liability Type | B1: Description | C1: Amount
A2: Payable | B2: Depositary invoice payable | C2: 0
A3: Accrued Fees | B3: Accrued management fees (daily) | C3: 16.02 | F3: 0.01
A4: Accrued Fees | B4: Accrued performance fees | C4: 1800
A5: Accrued Fees | B5: Accrued fees — Fund-of-Funds | C5: =+'Fund-of-Funds'!F5 -> 4.0027397
A6: TOTAL LIABILITIES | C6: =+SUM(C2:C5) -> 1820.0227

Sheet NAV Calculation
A1: Total Assets | B1: =+Assets!E9 -> 633150
A2: Total Liabilities | B2: =+Liabilities!C6 -> 1820.0227
A3: Net Asset Value | B3: =+B1-B2 -> 631329.98
A4: Number of Outstanding Shares | B4: =4480+385.86 -> 4865.86
A5: NAV per Share | B5: =+B3/B4 -> 129.74684

Sheet Fund-of-Funds
A1: Sub-fund | B1: Units held | C1: Sub-fund NAV per unit | D1: Annual sub-fund fee | E1: Market value | F1: Daily accrued fees
A2: Sub-fund A (bonds) | B2: 500 | C2: 105 | D2: 0.008 | E2: =+B2*C2 -> 52500 | F2: =+(E2*D2)/365 -> 1.1506849
A3: Sub-fund B (US equities) | B3: 300 | C3: 210 | D3: 0.012 | E3: =+B3*C3 -> 63000 | F3: =+(E3*D3)/365 -> 2.0712329
A4: Sub-fund C (emerging market equities) | B4: 200 | C4: 95 | D4: 0.015 | E4: =+B4*C4 -> 19000 | F4: =+(E4*D4)/365 -> 0.78082192
A5: TOTAL | E5: =+SUM(E2:E4) -> 134500 | F5: =+SUM(F2:F4) -> 4.0027397

Sheet Transaction Journal
A1: Date | B1: Transaction Type | C1: Description | D1: Debit account | E1: Credit account | F1: Amount
A2: 46273 | B2: Subscription | C2: Investor subscription | D2: Cash | E2: Share Capital | F2: 50000
A3: 46273 | B3: Dividend Income | C3: ASML dividend received | D3: Cash | E3: Income (Dividends) | F3: 800
A4: 46273 | B4: Fee Accrual | C4: Daily management fee accrual | D4: Management fees | E4: Accrued fees | F4: 16.02
A5: 46273 | B5: Interest Accrual | C5: Bond interest accrual | D5: Accrued Income | E5: Interest Income | F5: 1150
A6: 46273 | B6: Payment | C6: Depositary fee payment | D6: Payable | E6: Cash | F6: 2500

Sheet Trial Balance
A1: Account | B1: Total Debit | C1: Total Credit | D1: Net Balance
A2: Cash | B2: =+SUMIF('Transaction Journal'!D:D,A2,'Transaction Journal'!F:F) -> 50800 | C2: =+SUMIF('Transaction Journal'!E:E,A2,'Transaction Journal'!F:F) -> 2500 | D2: =+B2-C2 -> 48300
A3: Share Capital | B3: =+SUMIF('Transaction Journal'!D:D,A3,'Transaction Journal'!F:F) -> 0 | C3: =+SUMIF('Transaction Journal'!E:E,A3,'Transaction Journal'!F:F) -> 50000 | D3: =+B3-C3 -> -50000
A4: Income (Dividends) | B4: =+SUMIF('Transaction Journal'!D:D,A4,'Transaction Journal'!F:F) -> 0 | C4: =+SUMIF('Transaction Journal'!E:E,A4,'Transaction Journal'!F:F) -> 800 | D4: =+B4-C4 -> -800
A5: Management fees | B5: =+SUMIF('Transaction Journal'!D:D,A5,'Transaction Journal'!F:F) -> 16.02 | C5: =+SUMIF('Transaction Journal'!E:E,A5,'Transaction Journal'!F:F) -> 0 | D5: =+B5-C5 -> 16.02
A6: Accrued fees | B6: =+SUMIF('Transaction Journal'!D:D,A6,'Transaction Journal'!F:F) -> 0 | C6: =+SUMIF('Transaction Journal'!E:E,A6,'Transaction Journal'!F:F) -> 16.02 | D6: =+B6-C6 -> -16.02
A7: Accrued income | B7: =+SUMIF('Transaction Journal'!D:D,A7,'Transaction Journal'!F:F) -> 1150 | C7: =+SUMIF('Transaction Journal'!E:E,A7,'Transaction Journal'!F:F) -> 0 | D7: =+B7-C7 -> 1150
A8: Interest income | B8: =+SUMIF('Transaction Journal'!D:D,A8,'Transaction Journal'!F:F) -> 0 | C8: =+SUMIF('Transaction Journal'!E:E,A8,'Transaction Journal'!F:F) -> 1150 | D8: =+B8-C8 -> -1150
A9: Payable | B9: =+SUMIF('Transaction Journal'!D:D,A9,'Transaction Journal'!F:F) -> 2500 | C9: =+SUMIF('Transaction Journal'!E:E,A9,'Transaction Journal'!F:F) -> 0 | D9: =+B9-C9 -> 2500

Sheet Bank Statement
A1: Date | B1: Description | C1: Amount | D1: Balance
A2: 46273 | B2: Investor subscription received | C2: 50000 | D2: =+C2 -> 50000
A3: 46273 | B3: ASML dividend received | C3: 800 | D3: =+D2+C3 -> 50800
A4: 46274 | B4: Depositary fee payment | C4: -2500 | D4: =+D3+C4 -> 48300

Sheet TJ_Export
A1: Date | B1: Description | C1: Amount
A2: 46273 | B2: Investor subscription | C2: 50000
A3: 46273 | B3: ASML dividend received | C3: 800
A4: 46273 | B4: Depositary fee payment | C4: 2500
